CHANGES
LICENSE
MANIFEST.in
README.md
setup.py
sphinxcontrib/__init__.py
sphinxcontrib/drops.py
sphinxcontrib_spindrops.egg-info/PKG-INFO
sphinxcontrib_spindrops.egg-info/SOURCES.txt
sphinxcontrib_spindrops.egg-info/dependency_links.txt
sphinxcontrib_spindrops.egg-info/namespace_packages.txt
sphinxcontrib_spindrops.egg-info/not-zip-safe
sphinxcontrib_spindrops.egg-info/requires.txt
sphinxcontrib_spindrops.egg-info/top_level.txt