Metadata-Version: 1.1
Name: sphinxcontrib-spindrops
Version: 2.0
Summary: SpinDrops Sphinx extension
Home-page: https://gitlab.com/tesch1/sphinxcontrib-spindrops
Author: Michael Tesch
Author-email: tesch1@gmail.com
License: GPL
Download-URL: http://pypi.python.org/pypi/sphinxcontrib-spindrops
Platform: any
Classifier: Development Status :: 5 - Production/Stable
Classifier: Environment :: Console
Classifier: Environment :: Web Environment
Classifier: Intended Audience :: Developers
Classifier: Intended Audience :: Science/Research
Classifier: Operating System :: OS Independent
Classifier: Programming Language :: Python
Classifier: Topic :: Documentation
Classifier: Topic :: Utilities
